pyoptimum/__init__.py
pyoptimum/model.py
pyoptimum/portfolio.py
pyoptimum-0.12.0.dist-info/METADATA
pyoptimum-0.12.0.dist-info/WHEEL
pyoptimum-0.12.0.dist-info/licenses/LICENSE
pyoptimum-0.12.0.dist-info/RECORD
