Metadata-Version: 2.4
Name: pyoptimum
Version: 0.12.0
Summary: Python library for optimize.vicbee.net API
Project-URL: Homepage, https://github.com/mcdeoliveira/pyoptimum
Author-email: "Mauricio C. de Oliveira" <mcdeoliveira@duck.com>
License: MIT License
License-File: LICENSE
Keywords: Optimization,Porfolio Optimization
Classifier: Development Status :: 3 - Alpha
Classifier: Intended Audience :: Other Audience
Classifier: License :: OSI Approved :: MIT License
Classifier: Programming Language :: Python :: 3.8
Classifier: Topic :: Scientific/Engineering
Requires-Python: >3.7
Requires-Dist: aiohttp
Requires-Dist: numpy
Requires-Dist: pandas
Requires-Dist: requests
Requires-Dist: typing-extensions
